serviceengine/__init__.py
serviceengine/serviceengine.py
serviceengine/PublicFunctions/UpgradeCommand.py
serviceengine/PublicFunctions/__init__.py
serviceengine/PublicFunctions/CommandInterface/ICommand.py
serviceengine/PublicFunctions/CommandInterface/__init__.py
serviceengine/PublicFunctions/LanguageCommand/RunScriptCommand.py
serviceengine/PublicFunctions/LanguageCommand/__init__.py
serviceengine/PublicFunctions/ShellCommands/EchoCommand.py
serviceengine/PublicFunctions/ShellCommands/__init__.py
serviceengine/PublicFunctions/ShellCommands/ShellCommandExecutor/ShellCommandExecutor.py
serviceengine/PublicFunctions/ShellCommands/ShellCommandExecutor/__init__.py
serviceengine/PublicFunctions/SupportCommands/HelpCommand.py
serviceengine/PublicFunctions/SupportCommands/__init__.py
serviceengine/PublicFunctions/SystemCommands/AsyncCommand.py
serviceengine/PublicFunctions/SystemCommands/LoopCommand.py
serviceengine/PublicFunctions/SystemCommands/WaitCommand.py
serviceengine/PublicFunctions/SystemCommands/__init__.py
serviceengine/PublicFunctions/SystemCommands/ForEachCommands/AsyncForEachCommand.py
serviceengine/PublicFunctions/SystemCommands/ForEachCommands/ForEachCommand.py
serviceengine/PublicFunctions/SystemCommands/ForEachCommands/ForEachLogic.py
serviceengine/PublicFunctions/SystemCommands/ForEachCommands/__init__.py
serviceengine/System/__init__.py
serviceengine/System/CommandQueue/CommandQueue.py
serviceengine/System/CommandQueue/CommandQueueFactory.py
serviceengine/System/CommandQueue/__init__.py
serviceengine/System/Configurations/ConfigArchivist.py
serviceengine/System/Configurations/SystemConfig.py
serviceengine/System/Configurations/__init__.py
serviceengine/System/EndpointMap/EndpointMapper.py
serviceengine/System/EndpointMap/__init__.py
serviceengine/System/EnqueueAndRun/EnqueueAndRun.py
serviceengine/System/EnqueueAndRun/__init__.py
serviceengine/System/FileSystem/FileSystem.py
serviceengine/System/FileSystem/__init__.py
serviceengine-0.1.2.7.dist-info/LICENSE
serviceengine-0.1.2.7.dist-info/METADATA
serviceengine-0.1.2.7.dist-info/WHEEL
serviceengine-0.1.2.7.dist-info/top_level.txt
serviceengine-0.1.2.7.dist-info/RECORD
